[{"companycategory":"DeFi","companyurl":"https://sienna.network/jobs/","id":"sienna1","jobname":"Community manager","companyname":"Sienna","joburl":"https://sienna.network/jobs/","jobcategory":"MARKETING"},{"id":"elusiv1","companyname":"Elusiv","companyurl":"https://elusiv.io/jobs","joburl":"https://www.elusiv.io/jobs/4fe7d249","companycategory":"DeFi","jobcategory":"CRYPTOGRAPHY","jobname":"Cryptographer"},{"companyname":"Elusiv","jobcategory":"ENGINEERING","companyurl":"https://elusiv.io/jobs","companycategory":"DeFi","id":"elusiv2","jobname":"Developer Relations Manager","joburl":"https://www.elusiv.io/jobs/edb201c2"},{"companyurl":"https://jobs.lever.co/Espresso","companycategory":"DeFi","id":"espresso1","jobcategory":"RESEARCH","jobname":"Ecosystem Researcher","companyname":"Espresso Systems","joburl":"https://jobs.lever.co/Espresso/1f2ef1c0-6215-4876-a869-87c307a87731"},{"jobname":"Growth Marketing Lead","joburl":"https://jobs.lever.co/Espresso/7aa0e3a7-a598-42a3-a5ff-c46d39597439","companyurl":"https://jobs.lever.co/Espresso","jobcategory":"MARKETING","companyname":"Espresso Systems","companycategory":"DeFi","id":"espresso2"},{"companycategory":"DeFi","companyname":"Espresso Systems","jobname":"Security Engineering Lead","id":"espresso3","joburl":"https://jobs.lever.co/Espresso/135f4767-f690-41f8-9ab0-95fd9d398677","jobcategory":"SECURITY","companyurl":"https://jobs.lever.co/Espresso"},{"jobcategory":"ENGINEERING","companyname":"Espresso Systems","companyurl":"https://jobs.lever.co/Espresso","companycategory":"DeFi","id":"espresso4","jobname":"Software Engineer - Infrastructure","joburl":"https://jobs.lever.co/Espresso/bf359a02-5579-4d8b-a254-23c989f67af5"},{"companycategory":"DeFi","joburl":"https://www.silentresearchlabs.org/jobs/backend-system-engineer","jobcategory":"ENGINEERING","id":"silent1","jobname":"Front End Developer","companyname":"Silent Research Labs","companyurl":"https://www.silentresearchlabs.org/company/careers"},{"id":"silent2","jobname":"BackEnd Engineer","joburl":"https://www.silentresearchlabs.org/jobs/backend-system-engineer","jobcategory":"ENGINEERING","companycategory":"DeFi","companyname":"Silent Research Labs","companyurl":"https://www.silentresearchlabs.org/company/careers"},{"companycategory":"DeFi","companyurl":"https://www.silentresearchlabs.org/company/careers","joburl":"https://www.silentresearchlabs.org/jobs/digital-designer","jobcategory":"PRODUCT","companyname":"Silent Research Labs","id":"silent3","jobname":"Digital Designer"},{"id":"silent4","jobname":"Growth Marketer","joburl":"https://www.silentresearchlabs.org/jobs/growth-marketer","companyname":"Silent Research Labs","companyurl":"https://www.silentresearchlabs.org/company/careers","jobcategory":"MARKETING","companycategory":"DeFi"},{"joburl":"https://www.silentresearchlabs.org/jobs/legal-counsel","companyurl":"https://www.silentresearchlabs.org/company/careers","id":"silent5","jobname":"Legal Counsel","jobcategory":"OTHER","companycategory":"DeFi","companyname":"Silent Research Labs"},{"joburl":"https://wellfound.com/jobs/2221049-blockchain-architect","id":"panther1","companyname":" Panther Protocol","jobname":"Blockchain Architect","companyurl":"https://wellfound.com/company/panther-protocol/jobs","companycategory":"DeFi","jobcategory":"ENGINEERING"},{"joburl":"https://wellfound.com/jobs/2227585-full-stack-developer","jobname":"Full Stack Developer","id":"panther2","jobcategory":"ENGINEERING","companyurl":"https://wellfound.com/company/panther-protocol/jobs","companycategory":"DeFi","companyname":" Panther Protocol"},{"joburl":"https://wellfound.com/jobs/2227586-lead-front-end-developer","companyname":" Panther Protocol","companyurl":"https://wellfound.com/company/panther-protocol/jobs","jobname":"Lead Front-end Developer","jobcategory":"ENGINEERING","id":"panther3","companycategory":"DeFi"},{"jobcategory":"MARKETING","companyurl":"https://wellfound.com/company/panther-protocol/jobs","companycategory":"DeFi","companyname":" Panther Protocol","joburl":"https://wellfound.com/jobs/2811961-sr-marcomms-and-social-media-manager","id":"panther4","jobname":"Sr. Marcomms and Social Media Manager"},{"jobcategory":"MARKETING","companycategory":"DeFi","jobname":"Sr. Technical Writer","joburl":"https://wellfound.com/jobs/2811958-sr-technical-writer","companyname":" Panther Protocol","companyurl":"https://wellfound.com/company/panther-protocol/jobs","id":"panther5"},{"joburl":"https://wellfound.com/jobs/1863129-rust-engineer","jobcategory":"ENGINEERING","companyname":"Webb","companycategory":"DeFi","id":"webb1","jobname":"Rust Engineer","companyurl":"https://wellfound.com/company/webb-4/jobs"},{"id":"webb2","jobname":"Senior Cryptography Engineer","companyname":"Webb","companycategory":"DeFi","companyurl":"https://wellfound.com/company/webb-4/jobs","jobcategory":"CRYPTOGRAPHY","joburl":"https://wellfound.com/jobs/1241036-senior-cryptography-engineer"},{"companyname":"Webb","companyurl":"https://wellfound.com/company/webb-4/jobs","jobname":"Chief Technology Officer ","companycategory":"DeFi","jobcategory":"ENGINEERING","joburl":"https://wellfound.com/jobs/1635055-chief-technology-officer","id":"webb3"},{"joburl":"https://wellfound.com/jobs/1654000-product-manager","companyname":"Webb","companycategory":"DeFi","id":"webb4","jobname":"Product Manager ","companyurl":"https://wellfound.com/company/webb-4/jobs","jobcategory":"PRODUCT"},{"id":"renegade1","companycategory":"DeFi","jobcategory":"CRYPTOGRAPHY","joburl":"https://jobs.lever.co/renegade/d356c32f-7089-4460-89ac-88e351c024cd","companyname":"Renegade","jobname":"Cryptography Engineer","companyurl":"https://jobs.lever.co/renegade/"},{"jobcategory":"ENGINEERING","companyurl":"https://jobs.lever.co/renegade/","jobname":"Full-Stack Engineer","id":"renegade2","joburl":"https://jobs.lever.co/renegade/797c3a64-eb3d-4cf6-94e7-9eb22d602fcb","companyname":"Renegade","companycategory":"DeFi"},{"id":"renegade3","jobcategory":"ENGINEERING","jobname":"Systems Engineer","joburl":"https://jobs.lever.co/renegade/f2a7662d-3f0b-47a6-a9e6-c570e42cfb34","companyname":"Renegade","companyurl":"https://jobs.lever.co/renegade/","companycategory":"DeFi"},{"companyurl":"https://jobs.lever.co/renegade/","id":"renegade4","jobcategory":"PRODUCT","jobname":"Interface Designer","companyname":"Renegade","joburl":"https://jobs.lever.co/renegade/7e2d53d1-5b44-4865-8b3f-e01ca969df4e","companycategory":"DeFi"},{"companyurl":"https://jobs.lever.co/renegade/","companycategory":"DeFi","jobcategory":"MARKETING","joburl":"https://jobs.lever.co/renegade/fd980ba9-48de-4175-a74f-d83e02acbb82","jobname":"Technical Writer","companyname":"Renegade","id":"renegade5"},{"jobname":"Generalist","joburl":"https://jobs.lever.co/renegade/ff82656d-c8bf-484b-95a0-378f2795443d","id":"renegade6","jobcategory":"OTHER","companyname":"Renegade","companyurl":"https://jobs.lever.co/renegade/","companycategory":"DeFi"},{"joburl":"https://definer.freshteam.com/jobs/_xHgZlVUfKwQ/ui-ux-graphic-designer-remote","companyname":"DeFiner","companyurl":"https://definer.freshteam.com/jobs","jobcategory":"MARKETING","id":"definer1","companycategory":"DeFi","jobname":"UI UX Graphic Designer"},{"companycategory":"DeFi","companyname":"DeFiner","id":"definer2","joburl":"https://definer.freshteam.com/jobs/vHT0qxyd93Mn/definer-full-stack-developer-remote","jobcategory":"ENGINEERING","jobname":"Full Stack Developer","companyurl":"https://definer.freshteam.com/jobs"},{"jobname":"Entry Level Data Scientist","jobcategory":"PRODUCT","companyurl":"https://definer.freshteam.com/jobs","joburl":"https://definer.freshteam.com/jobs/t-xkJgq0RfpW/entry-level-data-scientist","id":"definer3","companycategory":"DeFi","companyname":"DeFiner"},{"joburl":"https://www.beldex.io/careers#En","companyname":"Beldex","companyurl":"https://www.beldex.io/careers#En","companycategory":"Currency","jobcategory":"MARKETING","id":"beldex1","jobname":"Community Manager"},{"companycategory":"Currency","jobcategory":"OPERATIONS","jobname":"Consultant / Advisor","joburl":"https://www.beldex.io/careers#En","companyurl":"https://www.beldex.io/careers#En","companyname":"Beldex","id":"beldex2"},{"id":"beldex3","companycategory":"Currency","jobname":"Blockchain Core Developer","joburl":"https://www.beldex.io/careers#En","jobcategory":"ENGINEERING","companyurl":"https://www.beldex.io/careers#En","companyname":"Beldex"},{"companycategory":"Infra","jobcategory":"ENGINEERING","companyname":"Nym","jobname":"Rust Engineer","id":"nym1","joburl":"https://nym.teamtailor.com/jobs/3559512-rust-engineer","companyurl":"https://nym.teamtailor.com/"},{"companycategory":"Infra","jobcategory":"ENGINEERING","jobname":"Full Stack Engineer","id":"nym2","companyurl":"https://nym.teamtailor.com/","joburl":"https://nym.teamtailor.com/jobs/3559420-full-stack-engineer","companyname":"Nym"},{"companyname":"Nym","jobname":"Lead JavaScript Developer","companyurl":"https://nym.teamtailor.com/","companycategory":"Infra","id":"nym3","joburl":"https://nym.teamtailor.com/jobs/3085170-lead-javascript-developer-open-source","jobcategory":"ENGINEERING"},{"jobcategory":"ENGINEERING","id":"calimero1","companyname":"Calimero","companyurl":"https://www.calimero.network/careers","companycategory":"Infra","jobname":"Rust Developer","joburl":"https://calimero-network.talentlyft.com/jobs/rust-developer-Gt4"},{"companyname":"Lit","companycategory":"Infra","jobcategory":"ENGINEERING","companyurl":"https://jobs.lever.co/litprotocol","id":"lit1","jobname":"Support Engineer","joburl":"https://jobs.lever.co/litprotocol/2260c34e-ca2b-4339-b1af-c05180a033f6"},{"joburl":"https://www.mysterium.network/senior-backend-developer","id":"mysterium1","jobcategory":"ENGINEERING","companyurl":"https://www.mysterium.network/careers","companyname":"Mysterium Network","companycategory":"Infra","jobname":"Senior Backend Developer"},{"companycategory":"Infra","jobname":"DevOps Engineer","joburl":"https://ata.careers/atanetwork/DevOps-Engineer-c151b3048c124fab9506ff2dd626983f","id":"automata1","jobcategory":"ENGINEERING","companyname":"Automata Network","companyurl":"https://ata.careers/"},{"joburl":"https://jobs.smartrecruiters.com/IntegriteeAG/743999851317541-full-stack-developer","companyurl":"https://www.integritee.network/about#join","jobname":"Full-Stack Developer","companyname":"Integritee","companycategory":"Infra","id":"integritee1","jobcategory":"ENGINEERING"},{"jobname":"Senior DevOps Engineer","companyurl":"https://www.integritee.network/about#join","companyname":"Integritee","companycategory":"Infra","joburl":"https://jobs.smartrecruiters.com/IntegriteeAG/743999851317371-senior-devops-engineer","id":"integritee2","jobcategory":"ENGINEERING"},{"companyname":"Integritee","id":"integritee3","companycategory":"Infra","companyurl":"https://www.integritee.network/about#join","jobname":"Rust Core Developer","jobcategory":"ENGINEERING","joburl":"https://jobs.smartrecruiters.com/IntegriteeAG/743999851315676-rust-core-developer"},{"companycategory":"Infra","jobname":"Rust App-Developer","jobcategory":"ENGINEERING","joburl":"https://jobs.smartrecruiters.com/IntegriteeAG/743999851316681-rust-app-developer","id":"integritee4","companyurl":"https://www.integritee.network/about#join","companyname":"Integritee"},{"jobname":"Senior Researcher","jobcategory":"RESEARCH","companyname":"Nulink","companyurl":"https://www.nulink.org/careers","companycategory":"Infra","joburl":"https://www.nulink.org/careers/senior-researcher","id":"nulink1"},{"id":"nulink2","companyname":"Nulink","companycategory":"Infra","jobname":"Senior Developer","joburl":"https://www.nulink.org/careers/senior-developer","companyurl":"https://www.nulink.org/careers","jobcategory":"ENGINEERING"},{"jobcategory":"MARKETING","jobname":"Marketing Manager","companyname":"Nulink","id":"nulink3","companyurl":"https://www.nulink.org/careers","companycategory":"Infra","joburl":"https://www.nulink.org/careers/marketing-manager"},{"companyurl":"https://www.horizen.io/careers/#section-open-positions","joburl":"https://www.linkedin.com/jobs/view/3880434571/","id":"horizen1","jobname":"Marketing Intelligence Analyst","jobcategory":"MARKETING","companyname":"Horizen","companycategory":"Infra"},{"id":"horizen2","joburl":"https://www.linkedin.com/jobs/view/3874394239/","jobname":"Web3 Business Development Manager - North America","jobcategory":"SALES","companyname":"Horizen","companyurl":"https://www.horizen.io/careers/#section-open-positions","companycategory":"Infra"},{"id":"horizen3","jobname":"Web3 Business Development Manager - EMEA","companycategory":"Infra","companyname":"Horizen","joburl":"https://www.linkedin.com/jobs/view/3874392728/","jobcategory":"SALES","companyurl":"https://www.horizen.io/careers/#section-open-positions"},{"jobcategory":"CRYPTOGRAPHY","companyname":"Horizen","id":"horizen4","jobname":"Senior Cryptographic Engineer","companyurl":"https://www.horizen.io/careers/#section-open-positions","companycategory":"Infra","joburl":"https://www.linkedin.com/jobs/view/3823031648/"},{"jobcategory":"SALES","id":"horizen5","jobname":"Web3 Business Development Manager - APAC","joburl":"https://www.linkedin.com/jobs/view/3874904524/","companyurl":"https://www.horizen.io/careers/#section-open-positions","companycategory":"Infra","companyname":"Horizen"},{"jobname":"General Application","id":"penumbra1","jobcategory":"OTHER","companyname":"Penumbra","joburl":"https://boards.greenhouse.io/penumbralabs/jobs/4884093004","companycategory":"Infra","companyurl":"https://boards.greenhouse.io/penumbralabs"},{"id":"mina1","jobname":"Senior Blockchain Operations and Project Manager","companyname":"Mina","companyurl":"https://apply.workable.com/mina-foundation/","companycategory":"Infra","jobcategory":"OPERATIONS","joburl":"https://apply.workable.com/mina-foundation/j/C19F616FD8/"},{"companyname":"Mina","companyurl":"https://apply.workable.com/mina-foundation/","companycategory":"Infra","id":"mina2","joburl":"https://apply.workable.com/mina-foundation/j/B5EE3F83C4/","jobname":"Finance Director - Strategic Accounting","jobcategory":"FINANCIAL"},{"joburl":"https://apply.workable.com/mina-foundation/j/43304D9360/","jobcategory":"ENGINEERING","companyurl":"https://apply.workable.com/mina-foundation/","companycategory":"Infra","id":"mina3","companyname":"Mina","jobname":"Senior Developer Relations Engineer"},{"companycategory":"Infra","jobcategory":"ENGINEERING","id":"mina4","joburl":"https://apply.workable.com/mina-foundation/j/9512BBA558/","companyname":"Mina","companyurl":"https://apply.workable.com/mina-foundation/","jobname":"Senior Typescript - Javascript Engineer"},{"companycategory":"Infra","id":"mina5","jobname":"Senior Technical Product Manager","joburl":"https://apply.workable.com/mina-foundation/j/290A5EEDB8/","jobcategory":"PRODUCT","companyname":"Mina","companyurl":"https://apply.workable.com/mina-foundation/"},{"jobcategory":"ENGINEERING","companyname":"Oasis Network","joburl":"https://boards.greenhouse.io/oasisnetwork/jobs/4346429005","companycategory":"Infra","jobname":"Developer Relations Engineer","companyurl":"https://boards.greenhouse.io/oasisnetwork","id":"oasis1"},{"joburl":"https://boards.greenhouse.io/oasisnetwork/jobs/4348296005","companycategory":"Infra","companyname":"Oasis Network","id":"oasis2","companyurl":"https://boards.greenhouse.io/oasisnetwork","jobcategory":"ENGINEERING","jobname":"Developer Relations Manager"},{"id":"oasis3","companyurl":"https://boards.greenhouse.io/oasisnetwork","companycategory":"Infra","companyname":"Oasis Network","joburl":"https://boards.greenhouse.io/oasisnetwork/jobs/4358939005","jobname":"Developer Relations Manager","jobcategory":"ENGINEERING"},{"jobname":"Senior Software Engineer - Core Platform","companyname":"Oasis Network","companyurl":"https://boards.greenhouse.io/oasisnetwork","companycategory":"Infra","joburl":"https://boards.greenhouse.io/oasisnetwork/jobs/4395552005","jobcategory":"ENGINEERING","id":"oasis4"},{"companyname":"Oasis Network","jobcategory":"ENGINEERING","companycategory":"Infra","id":"oasis5","jobname":"Senior Software Engineer - Smart Contracts","companyurl":"https://boards.greenhouse.io/oasisnetwork","joburl":"https://boards.greenhouse.io/oasisnetwork/jobs/4369218005"},{"id":"oasis6","companyname":"Oasis Network","companyurl":"https://boards.greenhouse.io/oasisnetwork","companycategory":"Infra","jobname":"Senior Software Engineer - Core Platform","joburl":"https://boards.greenhouse.io/oasisnetwork/jobs/4395553005","jobcategory":"ENGINEERING"},{"jobcategory":"ENGINEERING","companycategory":"Infra","id":"oasis7","joburl":"https://boards.greenhouse.io/oasisnetwork/jobs/4395552005","jobname":"Senior Software Engineer - Core Platform","companyname":"Oasis Network","companyurl":"https://boards.greenhouse.io/oasisnetwork"},{"jobname":"Communications Lead","companycategory":"Infra","companyurl":"https://boards.greenhouse.io/oasisnetwork","joburl":"https://boards.greenhouse.io/oasisnetwork/jobs/4397677005","id":"oasis8","companyname":"Oasis Network","jobcategory":"MARKETING"},{"companyname":"Oasis Network","jobname":"Communications Lead","companyurl":"https://boards.greenhouse.io/oasisnetwork","companycategory":"Infra","id":"oasis9","joburl":"https://boards.greenhouse.io/oasisnetwork/jobs/4397675005","jobcategory":"MARKETING"},{"jobcategory":"MARKETING","companyurl":"https://boards.greenhouse.io/oasisnetwork","id":"oasis10","companyname":"Oasis Network","companycategory":"Infra","jobname":"Content Writer","joburl":"https://boards.greenhouse.io/oasisnetwork/jobs/4397672005"},{"jobname":"Content Writer","jobcategory":"MARKETING","joburl":"https://boards.greenhouse.io/oasisnetwork/jobs/4397674005","id":"Oasis11","companyname":"Oasis Network","companyurl":"https://boards.greenhouse.io/oasisnetwork","companycategory":"Infra"},{"id":"oasis12","companycategory":"Infra","jobcategory":"MARKETING","joburl":"https://boards.greenhouse.io/oasisnetwork/jobs/4396828005","jobname":"Events Coordinator","companyname":"Oasis Network","companyurl":"https://boards.greenhouse.io/oasisnetwork"},{"companyurl":"https://boards.greenhouse.io/oasisnetwork","id":"oasis13","companyname":"Oasis Network","companycategory":"Infra","joburl":"https://boards.greenhouse.io/oasisnetwork/jobs/4397687005","jobcategory":"MARKETING","jobname":"Social Media Manager"},{"jobcategory":"MARKETING","companycategory":"Infra","jobname":"Video Creator","id":"oasis14","companyname":"Oasis Network","joburl":"https://boards.greenhouse.io/oasisnetwork/jobs/4369216005","companyurl":"https://boards.greenhouse.io/oasisnetwork"},{"companyurl":"https://boards.greenhouse.io/oasisnetwork","companycategory":"Infra","joburl":"https://boards.greenhouse.io/oasisnetwork/jobs/4402278005","jobcategory":"OPERATIONS","jobname":"Project Manager","id":"oasis15","companyname":"Oasis Network"},{"companyname":"Edge","companycategory":"Infra","id":"edge1","joburl":"https://docs.google.com/forms/d/e/1FAIpQLScL1y9P8me7OvgCAyxnktZfJTI1ymMKit4vihNogBA0LGLYjQ/viewform","companyurl":"https://edge.network/en/careers/","jobcategory":"OTHER","jobname":"General Application"},{"jobname":"Applied Network Researcher","joburl":"https://boards.greenhouse.io/nomos/jobs/5453089","id":"nomos1","jobcategory":"CRYPTOGRAPHY","companyname":"Nomos","companyurl":"https://nomos.tech/join-us/","companycategory":"Infra"},{"id":"nomos2","jobcategory":"CRYPTOGRAPHY","joburl":"https://boards.greenhouse.io/nomos/jobs/5664663","companyname":"Nomos","companycategory":"Infra","companyurl":"https://nomos.tech/join-us/","jobname":"Zero Knowledge Proof Researcher"},{"jobcategory":"ENGINEERING","companyname":"Ritual","companyurl":"https://boards.greenhouse.io/ritual","companycategory":"Infra","jobname":"Backend Engineer","id":"ritual1","joburl":"https://boards.greenhouse.io/ritual/jobs/4083926007"},{"companycategory":"Infra","id":"ritual2","jobname":"Growth Engineer","jobcategory":"MARKETING","joburl":"https://boards.greenhouse.io/ritual/jobs/4324604007","companyname":"Ritual","companyurl":"https://boards.greenhouse.io/ritual"},{"companycategory":"Infra","jobname":"Machine Learning Engineer","companyname":"Ritual","jobcategory":"ENGINEERING","id":"ritual3","companyurl":"https://boards.greenhouse.io/ritual","joburl":"https://boards.greenhouse.io/ritual/jobs/4029531007"},{"jobcategory":"ENGINEERING","companyname":"Ritual","companycategory":"Infra","jobname":"Smart Contract Engineer","companyurl":"https://boards.greenhouse.io/ritual","joburl":"https://boards.greenhouse.io/ritual/jobs/4135728007","id":"ritual4"},{"jobcategory":"OTHER","companyurl":"https://boards.greenhouse.io/ritual","companycategory":"Infra","joburl":"https://boards.greenhouse.io/ritual/jobs/4135918007","companyname":"Ritual","jobname":"General Application","id":"ritual5"},{"jobname":"Product Design Manager - UX/UI","companyname":"Daml","id":"daml1","companyurl":"https://boards.greenhouse.io/digitalasset","jobcategory":"PRODUCT","joburl":"https://boards.greenhouse.io/digitalasset/jobs/5718042","companycategory":"Infra"},{"companyname":"DarkFi","id":"darkfi1","jobname":"Developer","companyurl":"https://darkrenaissance.github.io/darkfi/dev/contrib/contrib.html#employment","jobcategory":"ENGINEERING","companycategory":"Infra","joburl":"https://darkrenaissance.github.io/darkfi/dev/contrib/contrib.html#employment"},{"jobname":"Proving Systems Security Engineer","joburl":"https://boards.eu.greenhouse.io/aztec/jobs/4258022101","jobcategory":"SECURITY","companyname":"Aztec","id":"aztec1","companyurl":"https://boards.eu.greenhouse.io/aztec","companycategory":"layer2"},{"id":"aztec2","joburl":"https://boards.eu.greenhouse.io/aztec/jobs/4303324101","jobcategory":"PRODUCT","companyname":"Aztec","companycategory":"layer2","jobname":"Ecosystem Lead","companyurl":"https://boards.eu.greenhouse.io/aztec"},{"joburl":"https://boards.eu.greenhouse.io/aztec/jobs/4292939101","id":"aztec3","companyurl":"https://boards.eu.greenhouse.io/aztec","jobcategory":"MARKETING","companyname":"Aztec","companycategory":"layer2","jobname":"Chief Marketing Officer"},{"joburl":"https://www.linkedin.com/jobs/view/3869617724/","jobcategory":"ENGINEERING","jobname":"Backend Blockchain Engineer","id":"cori1","companyname":"COTI","companyurl":"https://coti.io/careers","companycategory":"layer2"},{"companyname":"COTI","companycategory":"layer2","jobname":"Financial Controller","companyurl":"https://coti.io/careers","joburl":"https://www.linkedin.com/jobs/view/3827498673/","id":"coti2","jobcategory":"FINANCIAL"},{"companycategory":"layer2","id":"polybase1","joburl":"https://polybase.notion.site/Senior-Frontend-Engineer-TypeScript-React-06175a647cd2447881f2bc20dcdc6db7","jobname":"Senior Frontend Engineer","companyname":"Polybase","jobcategory":"ENGINEERING","companyurl":"https://polybaselabs.com/careers"},{"companycategory":"layer2","jobname":"Head of Marketing","joburl":"https://polybase.notion.site/Head-of-Marketing-fa176c7548b944d4870fa4bab9b58ddc","jobcategory":"MARKETING","companyurl":"https://polybaselabs.com/careers","id":"polybase2","companyname":"Polybase"},{"jobcategory":"ENGINEERING","id":"wasabi1","jobname":"C#/.NET DEVELOPER","joburl":"https://forms.monday.com/forms/c74d845ed91d937c4cea5d229e203cd5?r=use1","companyurl":"https://wasabiwallet.io/contribution.html","companyname":"Wasabi Wallet","companycategory":"Wallet"},{"companyname":"Frame","jobcategory":"SECURITY","jobname":"Lead Security Engineer","companycategory":"Wallet","companyurl":"https://framelabs.notion.site/Join-Frame-Labs-bf796117a50040159b61c092ad89870d","id":"frame1","joburl":"https://framelabs.notion.site/Lead-Security-Engineer-f790bb2de22f4b51b8e656080004389d"},{"id":"frame2","joburl":"https://framelabs.notion.site/Senior-Engineer-a40cc11086af41db932e1419d2ddd82b","jobcategory":"ENGINEERING","companyurl":"https://framelabs.notion.site/Join-Frame-Labs-bf796117a50040159b61c092ad89870d","companyname":"Frame","companycategory":"Wallet","jobname":"Senior Engineer"},{"joburl":"https://framelabs.notion.site/Full-stack-Engineer-4ec2d924306e49998aef1f37cf47a918","companyurl":"https://framelabs.notion.site/Join-Frame-Labs-bf796117a50040159b61c092ad89870d","companyname":"Frame","companycategory":"Wallet","jobname":"Full-stack Engineer","jobcategory":"ENGINEERING","id":"frame3"},{"companyurl":"https://framelabs.notion.site/Join-Frame-Labs-bf796117a50040159b61c092ad89870d","jobname":"web3 Engineer","joburl":"https://framelabs.notion.site/web3-Engineer-1298f5c79915463cb72693f2fea083d1","jobcategory":"ENGINEERING","id":"frame4","companycategory":"Wallet","companyname":"Frame"},{"companycategory":"Infra","jobname":"Marketing Lead - APAC","companyname":"Aleph Zero","jobcategory":"MARKETING","joburl":"https://careers.alephzero.org/companies/aleph-zero/jobs/33199728-marketing-lead-apac-m-f-div#content","id":"alephzero1","companyurl":"https://careers.alephzero.org/companies/aleph-zero#content"},{"companycategory":"Infra","jobname":"Frontend Engineer","joburl":"https://careers.alephzero.org/companies/aleph-zero/jobs/21105112-frontend-engineer-m-f-div#content","id":"alephzero2","jobcategory":"ENGINEERING","companyname":"Aleph Zero","companyurl":"https://careers.alephzero.org/companies/aleph-zero#content"},{"joburl":"https://careers.alephzero.org/companies/aleph-zero/jobs/20944514-software-developer-rust-m-f-div#content","companycategory":"Infra","id":"alephzero3","jobname":"Software Developer - Rust","jobcategory":"ENGINEERING","companyname":"Aleph Zero","companyurl":"https://careers.alephzero.org/companies/aleph-zero#content"},{"jobname":"Rust Developer","companyurl":"https://ethernity.cloud/company#careers","joburl":"https://ethernity.cloud/rust-developer.pdf","id":"ethernitycloud1","jobcategory":"ENGINEERING","companyname":"Ethernity Cloud","companycategory":"Computing"},{"companyname":"Ethernity Cloud","jobname":"Python Developer","companyurl":"https://ethernity.cloud/company#careers","id":"ethernitycloud2","jobcategory":"ENGINEERING","joburl":"https://ethernity.cloud/python-developer.pdf","companycategory":"Computing"},{"companycategory":"Computing","companyname":"Ethernity Cloud","id":"ethernitycloud3","joburl":"https://ethernity.cloud/devops.pdf","companyurl":"https://ethernity.cloud/company#careers","jobname":"DevOps Engineer","jobcategory":"ENGINEERING"},{"id":"chainreaction1","joburl":"https://chain-reaction.io/careers/co/taiwan/5D.34F/manufacturing-system-manager/all","jobname":"Manufacturing System Manager","companyurl":"https://chain-reaction.io/careers/","jobcategory":"PRODUCT","companyname":"Chain Reaction","companycategory":"Computing"},{"joburl":"https://chain-reaction.io/careers/co/usa-san-jose/79.240/sales-manager/all","companyurl":"https://chain-reaction.io/careers/","jobcategory":"SALES","companycategory":"Computing","jobname":"Sales Manager","id":"chainreaction2","companyname":"Chain Reaction"},{"id":"chainreaction3","jobcategory":"OTHER","companyname":"Chain Reaction","jobname":"Senior Supply Chain Specialist","joburl":"https://chain-reaction.io/careers/co/usa-san-jose/3A.14E/senior-supply-chain-specialist/all","companyurl":"https://chain-reaction.io/careers/","companycategory":"Computing"},{"jobcategory":"MARKETING","companyurl":"https://apply.workable.com/nillion/","id":"nillion1","joburl":"https://apply.workable.com/nillion/j/F12CD265F6/","companycategory":"Computing","companyname":"nillion","jobname":"Senior Content Marketing Manager"},{"id":"nillion2","companyurl":"https://apply.workable.com/nillion/","companyname":"nillion","jobname":"Senior Site Reliability Engineer ","joburl":"https://apply.workable.com/nillion/j/3BAA97E447/","jobcategory":"ENGINEERING","companycategory":"Computing"},{"id":"nillion3","jobname":"General Counsel ","companyname":"nillion","companyurl":"https://apply.workable.com/nillion/","companycategory":"Computing","joburl":"https://apply.workable.com/nillion/j/236F04047D/","jobcategory":"LEGAL"},{"id":"nillion4","companyname":"nillion","jobname":"Business Development Associate","joburl":"https://apply.workable.com/nillion/j/448AEE2508/","jobcategory":"SALES","companyurl":"https://apply.workable.com/nillion/","companycategory":"Computing"},{"id":"nillion5","companyurl":"https://apply.workable.com/nillion/","jobname":"Decentralized Infrastructure Engineer","jobcategory":"ENGINEERING","joburl":"https://apply.workable.com/nillion/j/29B4D07606/","companyname":"nillion","companycategory":"Computing"},{"jobcategory":"ENGINEERING","companyname":"nillion","joburl":"https://apply.workable.com/nillion/j/56D46BA9D6/","jobname":"Senior Distributed Systems Engineer","companyurl":"https://apply.workable.com/nillion/","companycategory":"Computing","id":"nillion6"},{"companycategory":"Computing","companyurl":"https://jobs.lever.co/ARPA","companyname":"ARPA","jobcategory":"ENGINEERING","id":"arpa1","jobname":"Software Engineer","joburl":"https://jobs.lever.co/ARPA/9c350538-5ab5-4e34-9aaf-15ecc91b784e"},{"joburl":"https://jobs.lever.co/ARPA/e54fe7e5-931f-4175-8610-a73fd998cbbd","id":"arpa2","jobcategory":"OPERATIONS","companyurl":"https://jobs.lever.co/ARPA","jobname":"Operations Analyst","companyname":"ARPA","companycategory":"Computing"},{"companyname":"ARPA","jobname":"Personal Assistant","jobcategory":"OPERATIONS","id":"arpa3","companyurl":"https://jobs.lever.co/ARPA","companycategory":"Computing","joburl":"https://jobs.lever.co/ARPA/64e198a0-652b-465f-85b6-2e3db1a865a0"},{"joburl":"https://jobs.lever.co/ARPA/71a817fc-afc9-424a-bba8-06a3aceb5a99","id":"arpa4","jobcategory":"OPERATIONS","companyname":"ARPA","jobname":"Digital Asset Hedge Fund Operations Associate","companyurl":"https://jobs.lever.co/ARPA","companycategory":"Computing"},{"companycategory":"Computing","companyurl":"https://jobs.lever.co/ARPA","companyname":"ARPA","joburl":"https://jobs.lever.co/ARPA/c9b402b9-c572-4abb-ac14-0c85045f0448","jobname":"Business Operations Associate","id":"arpa5","jobcategory":"MARKETING"},{"jobname":"Global Growth & Marketing Analyst Manager","companyname":"ARPA","companyurl":"https://jobs.lever.co/ARPA","id":"arpa6","jobcategory":"MARKETING","joburl":"https://jobs.lever.co/ARPA/6d6376af-6c16-454b-ad9c-17ef6a9b9e1a","companycategory":"Computing"},{"jobname":"Product Owner","companyurl":"https://jobs.lever.co/ARPA","companycategory":"Computing","jobcategory":"PRODUCT","companyname":"ARPA","id":"arpa7","joburl":"https://jobs.lever.co/ARPA/4faa3385-ee1e-4d2b-992b-91c620bc6492"},{"jobcategory":"MARKETING","companyurl":"https://foundation.xyz/jobs/","jobname":"Head of Growth","companyname":"Foundation","companycategory":"Hardware","id":"foundation1","joburl":"https://foundation.xyz/jobs/#jobCollapse1"},{"companyurl":"https://foundation.xyz/jobs/","jobname":"Rust UI & Apps Engineer","jobcategory":"PRODUCT","companyname":"Foundation","companycategory":"Hardware","joburl":"https://foundation.xyz/jobs/#jobCollapse2","id":"foundation2"},{"companyurl":"https://foundation.xyz/jobs/","jobcategory":"ENGINEERING","companycategory":"Hardware","id":"foundation3","joburl":"https://foundation.xyz/jobs/#jobCollapse3","companyname":"Foundation","jobname":"Embedded C Engineer"},{"companyurl":"https://foundation.xyz/jobs/","jobname":"Embedded Rust Device Driver Engineer","joburl":"https://foundation.xyz/jobs/#jobCollapse4","jobcategory":"ENGINEERING","companycategory":"Hardware","companyname":"Foundation","id":"foundation4"},{"companyname":"SpruceID","companyurl":"https://jobs.lever.co/sprucesystems","jobname":"Quality Engineer","joburl":"https://jobs.lever.co/sprucesystems/d05ebda3-49d3-46f2-8905-fb6b988de6ba","id":"spruceid1","jobcategory":"ENGINEERING","companycategory":"DID"},{"joburl":"https://jobs.lever.co/sprucesystems/dc335f4f-569d-4da8-a433-1f7d7a4aeef7","companycategory":"DID","id":"spruceid2","jobcategory":"ENGINEERING","jobname":"React Native Developer","companyname":"SpruceID","companyurl":"https://jobs.lever.co/sprucesystems"},{"jobcategory":"ENGINEERING","companycategory":"DID","jobname":"Site Reliability Engineer","companyurl":"https://jobs.lever.co/sprucesystems","id":"spruceid3","companyname":"SpruceID","joburl":"https://jobs.lever.co/sprucesystems/cc0863b6-f021-4e9f-b45b-4b407fc7515a"},{"companycategory":"DID","jobcategory":"ENGINEERING","companyname":"SpruceID","companyurl":"https://jobs.lever.co/sprucesystems","jobname":"Software Engineer - Android","id":"spruceid4","joburl":"https://jobs.lever.co/sprucesystems/d9129120-2757-4882-aec2-0d1a73441df6"},{"jobcategory":"ENGINEERING","companyurl":"https://jobs.lever.co/sprucesystems","companycategory":"DID","jobname":"Software Engineer - Rust","joburl":"https://jobs.lever.co/sprucesystems/c74507b7-a68b-41dd-83ad-b0162a538e16","companyname":"SpruceID","id":"spruceid5"},{"jobname":"Business Development - B2B","companyurl":"https://jobs.lever.co/sprucesystems","id":"spruceid6","jobcategory":"OPERATIONS","joburl":"https://jobs.lever.co/sprucesystems/09636ad4-682c-42e5-b0f6-95718fad6b23","companyname":"SpruceID","companycategory":"DID"},{"id":"spruceid7","companycategory":"DID","jobname":"Business Development - Public Sector","companyname":"SpruceID","companyurl":"https://jobs.lever.co/sprucesystems","joburl":"https://jobs.lever.co/sprucesystems/5f8b67a7-1003-478c-9be0-44562ff17a0f","jobcategory":"OPERATIONS"},{"jobname":"Senior Product Manager","id":"spruceid8","joburl":"https://jobs.lever.co/sprucesystems/72d43811-c6b0-478d-b647-b4caa03ce6d1","companyurl":"https://jobs.lever.co/sprucesystems","companyname":"SpruceID","jobcategory":"PRODUCT","companycategory":"DID"},{"jobname":"Technical Success Manager","jobcategory":"PRODUCT","companyurl":"https://jobs.lever.co/sprucesystems","companycategory":"DID","companyname":"SpruceID","id":"spruceid9","joburl":"https://jobs.lever.co/sprucesystems/c29dc4c8-5fe9-4b2d-8e15-b412c6c3d1ec"},{"id":"clique1","jobname":"Marketing Lead","joburl":"https://cliqueofficial.notion.site/Marketing-Lead-8a74a9cc9d064829bf947f8775130a2e","jobcategory":"MARKETING","companyurl":"https://cliqueofficial.notion.site/Clique-Careers-baf09f37cf2f412dad6fff88e61854b2","companyname":"Clique","companycategory":"DID"},{"jobname":"B2C Product Growth Lead","joburl":"https://cliqueofficial.notion.site/B2C-Product-Growth-Lead-a51db100789d4d349c8392aedb26481e","id":"clique2","companyname":"Clique","jobcategory":"MARKETING","companyurl":"https://cliqueofficial.notion.site/Clique-Careers-baf09f37cf2f412dad6fff88e61854b2","companycategory":"DID"},{"id":"c,lique3","joburl":"https://cliqueofficial.notion.site/B2B-Product-Manager-dd5d13d9e56e49ee8d1f03eddc05eebe","companyname":"Clique","companyurl":"https://cliqueofficial.notion.site/Clique-Careers-baf09f37cf2f412dad6fff88e61854b2","jobcategory":"PRODUCT","companycategory":"DID","jobname":"B2B Product Manager"},{"jobname":"Growth Operations","jobcategory":"OPERATIONS","companyurl":"https://cliqueofficial.notion.site/Clique-Careers-baf09f37cf2f412dad6fff88e61854b2","joburl":"https://cliqueofficial.notion.site/Growth-Operations-9cc08e57000f4890ae55d68e2a8ab2af","companyname":"Clique","id":"clique4","companycategory":"DID"},{"joburl":"https://cliqueofficial.notion.site/DeFi-Strategy-Lead-c5b7b3ab37e645d3908a81fd6f647e55","companyname":"Clique","companycategory":"DID","companyurl":"https://cliqueofficial.notion.site/Clique-Careers-baf09f37cf2f412dad6fff88e61854b2","jobname":"DeFi Strategy Lead","jobcategory":"MARKETING","id":"clique5"},{"id":"clique6","joburl":"https://cliqueofficial.notion.site/Cryptography-Engineer-eb197a293b4a47619c478da6dc12ef14","companycategory":"DID","jobname":"Cryptography Engineer","jobcategory":"ENGINEERING","companyurl":"https://cliqueofficial.notion.site/Clique-Careers-baf09f37cf2f412dad6fff88e61854b2","companyname":"Clique"},{"jobname":"Backend & Infra Engineer","companycategory":"DID","id":"clique7","companyname":"Clique","joburl":"https://cliqueofficial.notion.site/Backend-Infra-Engineer-6f3259cd79c640a4b57413d8429da07a","jobcategory":"ENGINEERING","companyurl":"https://cliqueofficial.notion.site/Clique-Careers-baf09f37cf2f412dad6fff88e61854b2"},{"jobname":"Senior Smart Contract Engineer","companyurl":"https://cliqueofficial.notion.site/Clique-Careers-baf09f37cf2f412dad6fff88e61854b2","companycategory":"DID","joburl":"https://cliqueofficial.notion.site/Senior-Smart-Contract-Engineer-d55d2f4b35334f8da46360879dfefbe7","companyname":"Clique","jobcategory":"ENGINEERING","id":"clique8"},{"joburl":"https://cliqueofficial.notion.site/Developer-Relations-cc30192067d64c85b7506fb8923a7524","jobname":"Developer Relations","jobcategory":"ENGINEERING","companycategory":"DID","companyurl":"https://cliqueofficial.notion.site/Clique-Careers-baf09f37cf2f412dad6fff88e61854b2","companyname":"Clique","id":"clique9"},{"jobcategory":"ENGINEERING","joburl":"https://cliqueofficial.notion.site/PWA-Engineer-280cd46d71a94340beb5163bcccec04c","jobname":"PWA Engineer","companyname":"Clique","companyurl":"https://cliqueofficial.notion.site/Clique-Careers-baf09f37cf2f412dad6fff88e61854b2","companycategory":"DID","id":"clique10"},{"jobcategory":"QA","jobname":"Testing Engineer","companyurl":"https://cliqueofficial.notion.site/Clique-Careers-baf09f37cf2f412dad6fff88e61854b2","companycategory":"DID","companyname":"Clique","joburl":"https://cliqueofficial.notion.site/Testing-Engineer-df4eb3b12c2e4fe7854edcaa83ff2054","id":"clique11"},{"jobname":"Full-Stack Engineer","id":"clique12","companyurl":"https://cliqueofficial.notion.site/Clique-Careers-baf09f37cf2f412dad6fff88e61854b2","companycategory":"DID","joburl":"https://cliqueofficial.notion.site/Full-Stack-Engineer-Browser-Extension-Specialist-04a192fd1b454be9bc2d2e9bf48a277b","jobcategory":"ENGINEERING","companyname":"Clique"},{"id":"sphereon1","joburl":"https://sphereon.com/job-openings-sales-executive/","companyname":"Sphereon","jobname":"Sales Executive","jobcategory":"SALES","companyurl":"https://sphereon.com/blockchain-job-openings-at-sphereon/","companycategory":"DID"},{"joburl":"https://sphereon.com/job-openings-for-software-developers/","jobcategory":"ENGINEERING","companyurl":"https://sphereon.com/blockchain-job-openings-at-sphereon/","companycategory":"DID","companyname":"Sphereon","id":"sphereon2","jobname":"Developer (senior)"},{"jobname":"Developer","id":"sphereon3","jobcategory":"ENGINEERING","companyname":"Sphereon","joburl":"https://sphereon.com/job-openings-for-software-developers/","companyurl":"https://sphereon.com/blockchain-job-openings-at-sphereon/","companycategory":"DID"},{"jobcategory":"ENGINEERING","companycategory":"DID","companyurl":"https://zkpass.gitbook.io/zkpass/supports/were-hiring","id":"zkpass1","companyname":"zkPass","jobname":"Software Engineer","joburl":"https://zkpass.gitbook.io/zkpass/supports/were-hiring"},{"jobname":"UX/UI Designer","joburl":"https://zkpass.gitbook.io/zkpass/supports/were-hiring","jobcategory":"PRODUCT","companyname":"zkPass","companycategory":"DID","companyurl":"https://zkpass.gitbook.io/zkpass/supports/were-hiring","id":"zkpass2"},{"id":"kilt1","jobname":"Software Developer Rust","companycategory":"DID","companyname":"KILT","jobcategory":"ENGINEERING","joburl":"https://www.kilt.io/about-us/careers","companyurl":"https://www.kilt.io/about-us/careers"},{"companyname":"Chainport","companyurl":"https://www.chainport.io/jobs","companycategory":"Bridge","joburl":"https://www.chainport.io/jobs","id":"chainport1","jobname":"Backend & DevOps Engineer","jobcategory":"ENGINEERING"},{"joburl":"https://www.chainport.io/jobs","jobname":"Cyber Security Specialist","jobcategory":"SECURITY","companyname":"Chainport","companycategory":"Bridge","companyurl":"https://www.chainport.io/jobs","id":"chainport2"},{"jobcategory":"MARKETING","companyname":"Chainport","companyurl":"https://www.chainport.io/jobs","companycategory":"Bridge","jobname":"Marketing Manager","joburl":"https://www.chainport.io/jobs","id":"chainport3"},{"id":"chainport4","joburl":"https://www.chainport.io/jobs","companyname":"Chainport","companycategory":"Bridge","companyurl":"https://www.chainport.io/jobs","jobname":"QA & Support Lead Engineer","jobcategory":"ENGINEERING"},{"jobname":"Senior Front-End Engineer","companycategory":"Bridge","companyname":"Chainport","joburl":"https://www.chainport.io/jobs","id":"chainport5","companyurl":"https://www.chainport.io/jobs","jobcategory":"ENGINEERING"},{"companycategory":"Messenging","companyurl":"https://waku.org/join-us/","jobname":"Protocol Engineer - Chat Messaging","joburl":"https://boards.greenhouse.io/waku/jobs/5607301","companyname":"Waku","id":"waku1","jobcategory":"ENGINEERING"},{"companyname":"Waku","id":"waku2","companyurl":"https://waku.org/join-us/","joburl":"https://boards.greenhouse.io/waku/jobs/5681154","companycategory":"Messenging","jobcategory":"ENGINEERING","jobname":"Protocol Engineer "},{"jobcategory":"RESEARCH","companycategory":"Messenging","companyurl":"https://waku.org/join-us/","jobname":"Protocol Research Engineer","companyname":"Waku","id":"waku3","joburl":"https://boards.greenhouse.io/waku/jobs/5673113"},{"joburl":"https://carbon.website/job/business-development/","jobname":"Business Development","id":"chromium1","jobcategory":"SALES","companyname":"Carbon","companyurl":"https://carbon.website/jobs/","companycategory":"Browser"},{"companycategory":"Browser","joburl":"https://carbon.website/job/ux-designer/","jobname":"UX Designer","id":"chromium2","jobcategory":"PRODUCT","companyname":"Carbon","companyurl":"https://carbon.website/jobs/"},{"joburl":"https://carbon.website/job/chromium-developer/","jobcategory":"ENGINEERING","companyname":"Carbon","jobname":"Chromium Developer","companyurl":"https://carbon.website/jobs/","companycategory":"Browser","id":"chromium3"},{"joburl":"https://www.pumabrowser.com/careers/ios-engineer","companyname":"Puma Browser","jobcategory":"ENGINEERING","companyurl":"https://www.pumabrowser.com/careers","jobname":"iOS Engineer","companycategory":"Browser","id":"puma1"},{"jobcategory":"ENGINEERING","id":"puma2","joburl":"https://www.pumabrowser.com/careers/android-engineer","jobname":"Android Engineer","companyname":"Puma Browser","companyurl":"https://www.pumabrowser.com/careers","companycategory":"Browser"},{"companyname":"Puma Browser","id":"puma3","companycategory":"Browser","jobname":"Head of Memes & Growth ","companyurl":"https://www.pumabrowser.com/careers","jobcategory":"MARKETING","joburl":"https://www.pumabrowser.com/careers/head-of-memes-growth"},{"joburl":"https://grapheneos.org/hiring","companyname":"Graphene OS","jobname":"GrapheneOS Remote Developer","companyurl":"https://grapheneos.org/hiring","id":"grapheneos1","jobcategory":"ENGINEERING","companycategory":"OS"},{"companyname":"Codex","companycategory":"Storage","companyurl":"https://codex.storage/join-us","id":"codex1","jobcategory":"SALES","joburl":"https://boards.greenhouse.io/codex/jobs/5453088","jobname":"Technical Business Development Lead"},{"companycategory":"Storage","joburl":"https://www.ethswarm.org/jobs/Software_Engineer_go_blockchain","id":"swarm1","companyname":"Swarm","jobname":"Software Engineer ","companyurl":"https://www.ethswarm.org/jobs","jobcategory":"ENGINEERING"},{"jobcategory":"QA","jobname":"QA Engineer","joburl":"https://www.ethswarm.org/jobs/qa-engineer","companyname":"Swarm","companyurl":"https://www.ethswarm.org/jobs","companycategory":"Storage","id":"swarm2"},{"jobcategory":"ENGINEERING","joburl":"https://www.ethswarm.org/jobs/senior-software-engineer-go","companyname":"Swarm","companyurl":"https://www.ethswarm.org/jobs","jobname":"Senior Software Engineer","id":"swarm3","companycategory":"Storage"},{"companyurl":"https://www.ethswarm.org/jobs","companycategory":"Storage","id":"swarm4","joburl":"https://www.ethswarm.org/jobs/grant-manager","jobname":"Grant Manager","jobcategory":"OPERATIONS","companyname":"Swarm"},{"id":"swarm5","companycategory":"Storage","joburl":"https://www.ethswarm.org/jobs/browser-extension-developer","jobname":"Browser extension developer","jobcategory":"ENGINEERING","companyurl":"https://www.ethswarm.org/jobs","companyname":"Swarm"},{"companyurl":"https://www.ethswarm.org/jobs","companycategory":"Storage","companyname":"Swarm","jobname":"JavaScript Developer","id":"swarm6","joburl":"https://www.ethswarm.org/jobs/javascript-developer-fairdrive","jobcategory":"ENGINEERING"},{"jobcategory":"ENGINEERING","jobname":"Site Reliability - DevOps Engineer","companyname":"Storj","companyurl":"https://www.storj.io/careers#open-positions","id":"storj1","companycategory":"Storage","joburl":"https://storj.bamboohr.com/careers/74?source=aWQ9MzM="},{"jobcategory":"OPERATIONS","jobname":"Channel Account Manager","joburl":"https://storj.bamboohr.com/careers/76?source=aWQ9MTg=","companyurl":"https://www.storj.io/careers#open-positions","companycategory":"Storage","companyname":"Storj","id":"storj2"},{"id":"storj3","jobcategory":"SALES","companyname":"Storj","companycategory":"Storage","joburl":"https://storj.bamboohr.com/careers/75?source=aWQ9MTg=","jobname":"Channel Sales Leader","companyurl":"https://www.storj.io/careers#open-positions"},{"id":"privy1","jobname":"Forward Deployed Engineer","companycategory":"Other","jobcategory":"ENGINEERING","companyname":"Privy","companyurl":"https://jobs.ashbyhq.com/privy","joburl":"https://jobs.ashbyhq.com/privy/be704bc4-74b7-45cc-9bab-bc150a6b2858"},{"companyurl":"https://jobs.ashbyhq.com/privy","joburl":"https://jobs.ashbyhq.com/privy/e3f2a7d0-0a54-46b3-97f6-e1d115ada3c6","companycategory":"Other","id":"privy2","jobname":"Senior/Staff Software Engineer - Backend","jobcategory":"ENGINEERING","companyname":"Privy"},{"joburl":"https://jobs.ashbyhq.com/privy/ef1c0cbc-b9e0-4de7-a9a6-9eb880b05844","jobcategory":"ENGINEERING","companyname":"Privy","jobname":"Senior/Staff Software Engineer - Fullstack","id":"privy3","companyurl":"https://jobs.ashbyhq.com/privy","companycategory":"Other"},{"jobcategory":"SECURITY","id":"privy4","jobname":"Senior/Staff Software Engineer - Security","companyname":"Privy","joburl":"https://jobs.ashbyhq.com/privy/3615fe17-f10c-477e-a246-43eb8fac4cb1","companyurl":"https://jobs.ashbyhq.com/privy","companycategory":"Other"},{"jobname":"Senior/Staff Software Engineer - Backend","joburl":"https://jobs.ashbyhq.com/privy/de86a764-558f-4729-8f7e-81371c80bb21","id":"privy5","companyname":"Privy","companycategory":"Other","jobcategory":"ENGINEERING","companyurl":"https://jobs.ashbyhq.com/privy"},{"companyname":"Privy","jobname":"Senior/Staff Software Engineer - Fullstack","companyurl":"https://jobs.ashbyhq.com/privy","companycategory":"Other","joburl":"https://jobs.ashbyhq.com/privy/8aeff2e1-1fdf-4123-ae81-3867507c239e","jobcategory":"ENGINEERING","id":"privy6"},{"jobcategory":"SECURITY","companyurl":"https://jobs.ashbyhq.com/privy","companyname":"Privy","jobname":"Senior/Staff Software Engineer - Security","companycategory":"Other","id":"privy7","joburl":"https://jobs.ashbyhq.com/privy/c46f2751-8b05-472c-aaac-9b095baf41b5"},{"companyname":"Privy","companyurl":"https://jobs.ashbyhq.com/privy","jobname":"Software Engineer - Go-to-Market","joburl":"https://jobs.ashbyhq.com/privy/e870656b-975b-4bdf-8572-aba9b7b51366","companycategory":"Other","id":"privy8","jobcategory":"ENGINEERING"},{"companyname":"Privy","id":"privy9","jobcategory":"OTHER","companyurl":"https://jobs.ashbyhq.com/privy","joburl":"https://jobs.ashbyhq.com/privy/f3ff2818-e67a-4999-a8da-a86079b218aa","jobname":"General Application","companycategory":"Other"},{"jobcategory":"MARKETING","jobname":"Junior Performance Marketing","id":"ethermail1","joburl":"https://ethermail.breezy.hr/p/41e88ec99d4101-junior-performance-marketing","companyname":"EtherMail","companyurl":"https://ethermail.breezy.hr/","companycategory":"Other"},{"companyurl":"https://ethermail.breezy.hr/","jobcategory":"SALES","companyname":"EtherMail","joburl":"https://ethermail.breezy.hr/p/58dbd4f0073201-sales-associate","id":"ethermail2","companycategory":"Other","jobname":"Sales Associate"},{"id":"ethermail3","jobname":"Senior Android Developer","companyurl":"https://ethermail.breezy.hr/","companycategory":"Other","jobcategory":"ENGINEERING","joburl":"https://ethermail.breezy.hr/p/fd98c0588d4d01-senior-android-developer","companyname":"EtherMail"},{"companyname":"EtherMail","jobname":"Senior iOS Developer","jobcategory":"ENGINEERING","companycategory":"Other","joburl":"https://ethermail.breezy.hr/p/eebf0c43212401-senior-ios-developer","id":"ethermail4","companyurl":"https://ethermail.breezy.hr/"},{"companyurl":"https://ethermail.breezy.hr/","companycategory":"Other","id":"ethermail5","jobname":"Web3 Community and CRM Manager","jobcategory":"MARKETING","companyname":"EtherMail","joburl":"https://ethermail.breezy.hr/p/7b7fde48b97d01-web3-community-and-crm-manager"},{"companycategory":"Other","id":"ethermail6","joburl":"https://ethermail.breezy.hr/p/5510fef8101401-head-finance-accounting","jobcategory":"FINANCIAL","companyname":"EtherMail","companyurl":"https://ethermail.breezy.hr/","jobname":"Head Finance & Accounting"},{"joburl":"https://mailchain.xyz/careers?gh_jid=4041747101","jobcategory":"ENGINEERING","companyname":"Mailchain","jobname":"Senior Protocol Engineer","companyurl":"https://mailchain.com/careers","companycategory":"Other","id":"mailchain1"},{"companyname":"Mailchain","joburl":"https://mailchain.xyz/careers?gh_jid=4091945101","jobcategory":"OTHER","id":"mailchain2","companyurl":"https://mailchain.com/careers","companycategory":"Other","jobname":"General Application"},{"joburl":"https://rotki.com/jobs/backend","companyname":"Rotki","companyurl":"https://rotki.com/jobs/","id":"rotki1","jobname":"Python Backend Developer","jobcategory":"ENGINEERING","companycategory":"Other"},{"jobname":"Vue.js - TypeScript Developer","companycategory":"Other","jobcategory":"ENGINEERING","companyname":"Rotki","companyurl":"https://rotki.com/jobs/","id":"rotki2","joburl":"https://rotki.com/jobs/frontend"},{"joburl":"https://rotki.com/jobs/ui-ux","companycategory":"Other","jobname":"UI/UX designer","id":"rotki3","jobcategory":"PRODUCT","companyname":"Rotki","companyurl":"https://rotki.com/jobs/"},{"companycategory":"Labs","jobname":"ZK Cryptography Engineer","companyname":"O(1) Labs","companyurl":"https://boards.greenhouse.io/o1labs","id":"o1labs1","joburl":"https://boards.greenhouse.io/o1labs/jobs/5149186004","jobcategory":"CRYPTOGRAPHY"},{"companyurl":"https://boards.greenhouse.io/o1labs","companycategory":"Labs","jobcategory":"ENGINEERING","companyname":"O(1) Labs","joburl":"https://boards.greenhouse.io/o1labs/jobs/5141177004","jobname":"Ecosystem Exploration Engineer","id":"O1labs2"},{"companyurl":"https://boards.greenhouse.io/o1labs","companyname":"O(1) Labs","id":"O1labs3","jobname":"Protocol Engineer","joburl":"https://boards.greenhouse.io/o1labs/jobs/4082783004","jobcategory":"ENGINEERING","companycategory":"Labs"},{"companycategory":"Labs","id":"O1labs4","jobname":"ZK Applications Solutions Architect","joburl":"https://boards.greenhouse.io/o1labs/jobs/5138503004","companyname":"O(1) Labs","jobcategory":"ENGINEERING","companyurl":"https://boards.greenhouse.io/o1labs"},{"joburl":"https://boards.greenhouse.io/o1labs/jobs/5091373004","companyurl":"https://boards.greenhouse.io/o1labs","companycategory":"Labs","jobcategory":"MARKETING","companyname":"O(1) Labs","id":"O1labs5","jobname":"Marketing and Communications Manager"},{"companyurl":"https://boards.greenhouse.io/o1labs","jobname":"Protocol Product Manager","companycategory":"Labs","companyname":"O(1) Labs","id":"o1labs6","joburl":"https://boards.greenhouse.io/o1labs/jobs/5127243004","jobcategory":"PRODUCT"},{"jobname":"Research Cryptographer & Mathematician","companycategory":"Labs","joburl":"https://heliax.dev/jobs/research-cryptographer-mathematician","id":"heliax1","jobcategory":"CRYPTOGRAPHY","companyname":"Heliax","companyurl":"https://heliax.dev/jobs"},{"companyurl":"https://heliax.dev/jobs","companycategory":"Labs","jobname":"Distributed Systems Theorist","id":"heliax2","joburl":"https://heliax.dev/jobs/distributed-systems-theorist","jobcategory":"RESEARCH","companyname":"Heliax"},{"companycategory":"Labs","joburl":"https://heliax.dev/jobs/engineering-security-lead","jobcategory":"SECURITY","id":"heliax3","jobname":"Engineering Security Lead","companyname":"Heliax","companyurl":"https://heliax.dev/jobs"},{"jobcategory":"ENGINEERING","id":"heliax4","jobname":"Senior Engineer","joburl":"https://heliax.dev/jobs/senior-engineer","companyname":"Heliax","companyurl":"https://heliax.dev/jobs","companycategory":"Labs"},{"jobname":"Community Manager (Anoma/Namada)","id":"heliax5","jobcategory":"MARKETING","companycategory":"Labs","joburl":"https://heliax.dev/jobs/community-manager","companyurl":"https://heliax.dev/jobs","companyname":"Heliax"},{"id":"heliax6","joburl":"https://heliax.dev/jobs/anoma-application-researcher","companyurl":"https://heliax.dev/jobs","companycategory":"Labs","jobname":"Anoma Application Researcher","companyname":"Heliax","jobcategory":"RESEARCH"},{"id":"heliax7","joburl":"https://docs.google.com/forms/d/e/1FAIpQLSfTfzqkyp01uRTUl2kLVpwgjDCvCRiJiawcetrF9COjVjwCQg/viewform","jobcategory":"OTHER","companyname":"Heliax","companyurl":"https://heliax.dev/jobs","jobname":"General Application","companycategory":"Labs"},{"jobcategory":"ENGINEERING","companyurl":"https://chainsafe.io/careers#cta","companycategory":"Labs","jobname":"Developer Relations - Sygma","companyname":"ChainSafe","joburl":"https://boards.greenhouse.io/chainsafesystems/jobs/5130627004","id":"chainsafe1"},{"jobname":"DeveRel - Solutions Engineer","joburl":"https://boards.greenhouse.io/chainsafesystems/jobs/5140905004","jobcategory":"ENGINEERING","companyurl":"https://chainsafe.io/careers#cta","companycategory":"Labs","companyname":"ChainSafe","id":"chainsfe2"},{"jobcategory":"ENGINEERING","jobname":"Head of Protocol Engineering","companyurl":"https://chainsafe.io/careers#cta","joburl":"https://boards.greenhouse.io/chainsafesystems/jobs/5087051004","companycategory":"Labs","id":"chainsafe3","companyname":"ChainSafe"},{"id":"chainsafe4","jobname":"Protocol Engineer - Gossamer/Polkadot (Go)","joburl":"https://boards.greenhouse.io/chainsafesystems/jobs/5095606004","jobcategory":"ENGINEERING","companyname":"ChainSafe","companyurl":"https://chainsafe.io/careers#cta","companycategory":"Labs"},{"companyurl":"https://chainsafe.io/careers#cta","joburl":"https://boards.greenhouse.io/chainsafesystems/jobs/5004247004","companycategory":"Labs","jobcategory":"ENGINEERING","jobname":"Senior Golang Engineer - Bridge Ops and Production Support","companyname":"ChainSafe","id":"chainsafe5"},{"joburl":"https://boards.greenhouse.io/chainsafesystems/jobs/5140281004","jobcategory":"ENGINEERING","companyname":"ChainSafe","companyurl":"https://chainsafe.io/careers#cta","jobname":"Senior Product Manager - Lodestar/Ethereum","companycategory":"Labs","id":"chainsafe6"},{"companyname":"Synonym","jobname":"Product designer","joburl":"https://synonym.to/team","companycategory":"Labs","jobcategory":"PRODUCT","companyurl":"https://synonym.to/team","id":"synonym1"},{"jobname":"Head of Legal","jobcategory":"LEGAL","companyname":"XMTP","companycategory":"Labs","joburl":"https://boards.greenhouse.io/xmtp/jobs/4987831004","companyurl":"https://blog.xmtp.com/careers/","id":"xmtp1"},{"jobcategory":"CRYPTOGRAPHY","id":"pse1","jobname":"ZK Circuits Engineer","companyurl":"https://jobs.lever.co/ethereumfoundation/?department=Ethereum Foundation&team=Privacy and Scaling Explorations","companycategory":"Labs","joburl":"https://jobs.lever.co/ethereumfoundation/7a7da3a9-a080-40a9-8aed-9e81641650a4","companyname":"Privacy & Scaling Explorations"},{"companyurl":"https://jobs.lever.co/MantaNetwork","joburl":"https://jobs.lever.co/MantaNetwork/77e5faf9-7168-47ae-aae8-d518cf7f13e8","id":"P0x2","jobcategory":"MARKETING","companyname":"p0x Labs","companycategory":"Labs","jobname":"Russian Language Community Manager"},{"companyname":"p0x Labs","jobname":"Cryptography Engineer","companyurl":"https://jobs.lever.co/MantaNetwork","companycategory":"Labs","joburl":"https://jobs.lever.co/MantaNetwork/4d5abd3e-80da-49dd-b576-8f0a1250f56a","id":"P0x3","jobcategory":"CRYPTOGRAPHY"},{"companyurl":"https://jobs.lever.co/MantaNetwork","companycategory":"Labs","jobcategory":"SECURITY","companyname":"p0x Labs","id":"P0x4","jobname":"Senior Blockchain Security Engineer","joburl":"https://jobs.lever.co/MantaNetwork/d06720a5-08ff-42c7-bb22-201d511676df"},{"joburl":"https://jobs.lever.co/MantaNetwork/53c66d9f-ab2b-4270-bc30-aa1c3e912028","jobcategory":"MARKETING","companyname":"p0x Labs","companyurl":"https://jobs.lever.co/MantaNetwork","companycategory":"Labs","jobname":"Community Manager","id":"P0x5"},{"joburl":"https://jobs.lever.co/MantaNetwork/cff03de4-ee16-4944-8d5a-2399db4d843c","id":"P0x6","jobname":"Community Manager (Korea)","companyurl":"https://jobs.lever.co/MantaNetwork","jobcategory":"MARKETING","companyname":"p0x Labs","companycategory":"Labs"},{"id":"P0x7","companyurl":"https://jobs.lever.co/MantaNetwork","companyname":"p0x Labs","jobname":"Marketing Associate","joburl":"https://jobs.lever.co/MantaNetwork/3e2cc613-3b39-47d5-96b4-da0a8f28a123","jobcategory":"MARKETING","companycategory":"Labs"},{"companycategory":"Labs","joburl":"https://jobs.lever.co/MantaNetwork/ee99ecca-aafa-4505-92bb-d57df151c2db","companyname":"p0x Labs","jobcategory":"MARKETING","companyurl":"https://jobs.lever.co/MantaNetwork","id":"P0x8","jobname":"Technical Content Writer"},{"jobcategory":"MARKETING","companyname":"p0x Labs","companyurl":"https://jobs.lever.co/MantaNetwork","joburl":"https://jobs.lever.co/MantaNetwork/48981509-5b7e-4ebf-a9d7-6ad972e62e94","companycategory":"Labs","id":"P0x9","jobname":"Strategy Officer"},{"companyname":"p0x Labs","companycategory":"Labs","companyurl":"https://jobs.lever.co/MantaNetwork","jobname":"Product Manager","joburl":"https://jobs.lever.co/MantaNetwork/04581756-7424-4cd5-8c0e-6a2e294374ac","id":"p0x10","jobcategory":"PRODUCT"},{"joburl":"https://nil.foundation/careers/jobs?jobId=P1ZaI_Tx7oei","companyname":"nil Foundation","companyurl":"https://nil.foundation/careers/jobs","companycategory":"Labs","jobname":"C++ Developer","jobcategory":"ENGINEERING","id":"nilfoundation1"},{"jobname":"Cryptography Researcher","joburl":"https://nil.foundation/careers/jobs?jobId=eKBawSyO9EDP","companyname":"nil Foundation","companyurl":"https://nil.foundation/careers/jobs","companycategory":"Labs","id":"Nilfoundation2","jobcategory":"RESEARCH"},{"jobname":"Decentralized Applications Developer","joburl":"https://nil.foundation/careers/jobs?jobId=k-rjW4Y07Oce","jobcategory":"ENGINEERING","companyname":"nil Foundation","companyurl":"https://nil.foundation/careers/jobs","companycategory":"Labs","id":"Nilfoundation3"},{"jobcategory":"RESEARCH","jobname":"Decentralized Systems Researcher","companycategory":"Labs","joburl":"https://nil.foundation/careers/jobs?jobId=EsCDSlJdtwl5","id":"Nilfoundation4","companyurl":"https://nil.foundation/careers/jobs","companyname":"nil Foundation"},{"companyurl":"https://nil.foundation/careers/jobs","id":"Nilfoundation5","companycategory":"Labs","jobname":"DevOps Engineer ","companyname":"nil Foundation","joburl":"https://nil.foundation/careers/jobs?jobId=T_7OQ66Me3f8","jobcategory":"ENGINEERING"},{"jobcategory":"ENGINEERING","companycategory":"Labs","joburl":"https://nil.foundation/careers/jobs?jobId=P028ELR8t25y","jobname":"Engineering Director - Engineering manager","companyname":"nil Foundation","companyurl":"https://nil.foundation/careers/jobs","id":"Nilfoundation6"},{"id":"Nilfoundation7","jobcategory":"ENGINEERING","joburl":"https://nil.foundation/careers/jobs?jobId=bNn8gZTFIYEC","companyname":"nil Foundation","companycategory":"Labs","companyurl":"https://nil.foundation/careers/jobs","jobname":"Integration Engineer"},{"jobcategory":"RESEARCH","companyname":"nil Foundation","companycategory":"Labs","id":"Nilfoundation8","companyurl":"https://nil.foundation/careers/jobs","jobname":"Research Analyst","joburl":"https://nil.foundation/careers/jobs?jobId=lvuCF87ZKVN6"},{"companycategory":"Labs","jobname":"Senior C++ Developer","id":"Nilfoundation9","jobcategory":"ENGINEERING","joburl":"https://nil.foundation/careers/jobs?jobId=IpNIuwrbvK2s","companyname":"nil Foundation","companyurl":"https://nil.foundation/careers/jobs"},{"jobname":"Senior Go Developer","id":"Nilfoundation10","joburl":"https://nil.foundation/careers/jobs?jobId=i6jHoMRVSmtn","jobcategory":"ENGINEERING","companyname":"nil Foundation","companyurl":"https://nil.foundation/careers/jobs","companycategory":"Labs"},{"companyurl":"https://nil.foundation/careers/jobs","companycategory":"Labs","id":"Nilfoundation11","jobname":"Developer Advocate","joburl":"https://nil.foundation/careers/jobs?jobId=G6kpKrDN9dEJ","jobcategory":"ENGINEERING","companyname":"nil Foundation"},{"jobcategory":"ENGINEERING","companycategory":"Labs","companyname":"nil Foundation","companyurl":"https://nil.foundation/careers/jobs","id":"Nilfoundation12","jobname":"Head of DevRel","joburl":"https://nil.foundation/careers/jobs?jobId=ED8N-i_eiVbU"},{"companyname":"nil Foundation","jobname":"Growth manager","companyurl":"https://nil.foundation/careers/jobs","jobcategory":"MARKETING","id":"Nilfoundation13","companycategory":"Labs","joburl":"https://nil.foundation/careers/jobs?jobId=Ov_R2SNwii0-"},{"id":"Nilfoundation14","joburl":"https://nil.foundation/careers/jobs?jobId=f5KSNsuUZ99v","jobname":"Head of Ecosystem","companyurl":"https://nil.foundation/careers/jobs","companycategory":"Labs","jobcategory":"MARKETING","companyname":"nil Foundation"},{"jobcategory":"ENGINEERING","companyurl":"https://vac.dev/join-us","id":"vac1","companyname":"Vac","companycategory":"Other","jobname":"Libp2p Networking Engineer","joburl":"https://boards.greenhouse.io/logos/jobs/5688077"},{"joburl":"https://boards.greenhouse.io/logos/jobs/5700881","id":"vac2","jobname":"Software Developer in Test (Rust or Go)","jobcategory":"ENGINEERING","companyname":"Vac","companyurl":"https://vac.dev/join-us","companycategory":"Other"},{"jobcategory":"RESEARCH","companyurl":"https://vac.dev/join-us","companyname":"Vac","jobname":"Token Economics Specialist (Vac TKE)","companycategory":"Other","id":"vac3","joburl":"https://boards.greenhouse.io/logos/jobs/5730039"},{"joburl":"https://boards.greenhouse.io/logos/jobs/5543923","jobcategory":"RESEARCH","companyname":"Vac","companyurl":"https://vac.dev/join-us","companycategory":"Other","id":"vac4","jobname":"Zero Knowledge Research Engineer (Vac ACZ)"},{"id":"vac5","joburl":"https://boards.greenhouse.io/logos/jobs/5543854","jobcategory":"RESEARCH","companycategory":"Other","jobname":"Zero Knowledge Research Engineer (Vac Nescience)","companyname":"Vac","companyurl":"https://vac.dev/join-us"},{"jobname":"Zero Knowledge Researcher (Vac Nescience)","joburl":"https://boards.greenhouse.io/logos/jobs/4460860","id":"vac6","companyname":"Vac","companyurl":"https://vac.dev/join-us","companycategory":"Other","jobcategory":"RESEARCH"},{"id":"dusk1","companyurl":"https://dusk.network/career/other-roles/","companycategory":"DarkFi","jobcategory":"OTHER","companyname":"Dusk","jobname":"General Application","joburl":"https://dusk.network/career/other-roles/"},{"companycategory":"Infra","id":"zama1","jobcategory":"ENGINEERING","joburl":"https://jobs.zama.ai/companies/zama/jobs/software-engineer-secure-enclaves_paris","companyname":"Zama","companyurl":"https://jobs.zama.ai/","jobname":"Senior Software Engineer - KMS"},{"jobname":"Blockchain Engineer - Backend","jobcategory":"ENGINEERING","companycategory":"Infra","companyurl":"https://jobs.zama.ai/","joburl":"https://jobs.zama.ai/companies/zama/jobs/blockchain-engineer-backend_paris","companyname":"Zama","id":"zama2"},{"companyname":"Zama","id":"zama3","companyurl":"https://jobs.zama.ai/","companycategory":"Infra","jobname":"FPGA - Hardware Engineer","joburl":"https://jobs.zama.ai/companies/zama/jobs/rtl-design-engineer_paris","jobcategory":"ENGINEERING"},{"jobcategory":"SALES","id":"zama4","jobname":"Business Development Director - Financial Institutions","companyname":"Zama","companyurl":"https://jobs.zama.ai/","joburl":"https://jobs.zama.ai/companies/zama/jobs/business-development-director-us-blockchain_paris","companycategory":"Infra"},{"companycategory":"Infra","joburl":"https://jobs.zama.ai/companies/zama/jobs/senior-researcher-cryptography_paris","jobcategory":"RESEARCH","id":"zama5","jobname":"Homomorphic Encryption Researcher","companyname":"Zama","companyurl":"https://jobs.zama.ai/"},{"companyurl":"https://jobs.zama.ai/","companycategory":"Infra","companyname":"Zama","joburl":"https://jobs.zama.ai/companies/zama/jobs/gpu-engineer_paris","jobname":"GPU Engineer","jobcategory":"ENGINEERING","id":"zama6"},{"joburl":"https://kelp.notion.site/Web-Developer-Svelte-SvelteKit-GraphQL-Tailwind-100-Remote-4a890c0a7c6c4208a68ff2eb25648c46","jobcategory":"ENGINEERING","companyname":"Kelp","id":"kelp1","companycategory":"DID","companyurl":"https://kelp.notion.site/Kelp-Anagolay-Careers-c27cebdedf29461abda591bc23bad3f6","jobname":"Web Developer"},{"jobname":"Backend Developer","jobcategory":"ENGINEERING","id":"kelp2","companyurl":"https://kelp.notion.site/Kelp-Anagolay-Careers-c27cebdedf29461abda591bc23bad3f6","joburl":"https://kelp.notion.site/Backend-Developer-TypeScript-GraphQL-NodeJS-100-Remote-c2eb6a29bc8e41dab370d5e8f0c83327","companyname":"Kelp","companycategory":"DID"},{"id":"kelp3","companyurl":"https://kelp.notion.site/Kelp-Anagolay-Careers-c27cebdedf29461abda591bc23bad3f6","companycategory":"DID","jobcategory":"MARKETING","companyname":"Kelp","joburl":"https://kelp.notion.site/Marketing-Community-Architect-351c7c1ffcc24a2c9e1a13a48b47cc42","jobname":"Marketing & Community Architect"},{"joburl":"https://kelp.notion.site/Technical-Writer-1807fce2f97b4ba19da2454931ad5224","id":"kelp4","jobname":"Technical Writer","jobcategory":"MARKETING","companycategory":"DID","companyurl":"https://kelp.notion.site/Kelp-Anagolay-Careers-c27cebdedf29461abda591bc23bad3f6","companyname":"Kelp"},{"jobname":"Head of Sales","id":"cheqd1","companyurl":"https://careers.cheqd.io/jobs","joburl":"https://careers.cheqd.io/jobs/SWe0EVpvHKqR/head-of-sales-bd-remote","jobcategory":"SALES","companyname":"Cheqd","companycategory":"DID"},{"companycategory":"Storage","jobcategory":"ENGINEERING","companyurl":"https://transferchain.io/careers","joburl":"https://angel.co/company/transferchain/jobs/668540-backend-developer","jobname":"Backend Developer","companyname":"TransferChain","id":"transferchain1"},{"joburl":"https://angel.co/company/transferchain/jobs/668542-frontend-developer","companyurl":"https://transferchain.io/careers","companycategory":"Storage","id":"transferchain2","companyname":"TransferChain","jobname":"Frontend Developer","jobcategory":"ENGINEERING"},{"companyname":"TransferChain","jobcategory":"ENGINEERING","joburl":"https://angel.co/company/transferchain/jobs/770496-devops-engineer","jobname":"DevOps Engineer","companycategory":"Storage","companyurl":"https://transferchain.io/careers","id":"transferchain3"},{"companyname":"TransferChain","companyurl":"https://transferchain.io/careers","joburl":"https://angel.co/company/transferchain/jobs/676453-market-segmentation-and-customer-retention-specialist","companycategory":"Storage","jobname":"Market Segmentation and Customer Retention Specialist","jobcategory":"MARKETING","id":"transferchain4"},{"companycategory":"Storage","jobcategory":"OTHER","companyurl":"https://transferchain.io/careers","joburl":"https://angel.co/company/transferchain/jobs/673388-general-application","jobname":"General Application","companyname":"TransferChain","id":"transferchain5"},{"joburl":"https://join.com/companies/doxychain/spontaneous-application","companycategory":"Other","companyname":"DoxyChain","companyurl":"https://join.com/companies/doxychain","id":"doxychain1","jobname":"General Application","jobcategory":"OTHER"},{"id":"osom1","companycategory":"Labs","jobname":"Junior Software Engineer","companyurl":"https://www.osomprivacy.com/jobs","jobcategory":"ENGINEERING","joburl":"https://jobs.lever.co/osomprivacy/ba042a15-eee4-410a-9c8c-7cb01d1e8391","companyname":"OSOM"},{"id":"osom2","companyname":"OSOM","jobcategory":"ENGINEERING","companyurl":"https://www.osomprivacy.com/jobs","jobname":"Modem Specialist","joburl":"https://jobs.lever.co/osomprivacy/220b2725-2787-4e01-a430-ecf4a1e5b628","companycategory":"Labs"},{"jobname":"Modem - Cellular System Test Engineer","joburl":"https://jobs.lever.co/osomprivacy/acf278c2-592c-4b9d-b351-3473313f7135","jobcategory":"ENGINEERING","companyurl":"https://www.osomprivacy.com/jobs","id":"osom3","companyname":"OSOM","companycategory":"Labs"},{"companyurl":"https://www.osomprivacy.com/jobs","jobname":"Program Manager - Software","jobcategory":"ENGINEERING","joburl":"https://jobs.lever.co/osomprivacy/03f3bc37-11f7-4938-8d29-04c55ce1dc9f","id":"osom4","companyname":"OSOM","companycategory":"Labs"},{"companyurl":"https://www.fyeo.io/careers","id":"fyeo1","companyname":"FYEO","jobcategory":"CRYPTOGRAPHY","joburl":"https://www.fyeo.io/careers-senior-cryptographer","companycategory":"DID","jobname":" Senior Cryptographer"},{"id":"fyeo2","jobname":"Senior Blockchain Developer","joburl":"https://www.fyeo.io/careers-senior-blockchain-developer","companyname":"FYEO","jobcategory":"ENGINEERING","companyurl":"https://www.fyeo.io/careers","companycategory":"DID"},{"companyurl":"https://www.fyeo.io/careers","jobcategory":"ENGINEERING","companycategory":"DID","companyname":"FYEO","jobname":" React/NodeJS/GraphQL Engineer","joburl":"https://www.fyeo.io/careers-react-nodejs-graphql-engineer","id":"fyeo3"},{"companycategory":"DID","jobname":" DevOps Engineer","companyurl":"https://www.fyeo.io/careers","jobcategory":"ENGINEERING","companyname":"FYEO","joburl":"https://www.fyeo.io/careers-devops-engineer","id":"fyeo4"},{"joburl":"https://www.fyeo.io/careers-python-backend-engineer","jobname":" Python Backend Engineer","companyurl":"https://www.fyeo.io/careers","companyname":"FYEO","companycategory":"DID","jobcategory":"ENGINEERING","id":"fyeo5"},{"companyurl":"https://www.fyeo.io/careers","companycategory":"DID","jobname":" Senior Web Engineer - Browser Extension Lead","jobcategory":"ENGINEERING","joburl":"https://www.fyeo.io/senior-web-engineer-browser-extension-lead","companyname":"FYEO","id":"fyeo6"},{"companyurl":"https://www.fyeo.io/careers","companycategory":"DID","joburl":"https://www.fyeo.io/careers-osint-security-analyst","jobname":" OSINT Security Analyst","jobcategory":"SECURITY","id":"fyeo7","companyname":"FYEO"},{"jobname":"Head of Growth","joburl":"https://www.fyeo.io/careers-head-of-growth","jobcategory":"MARKETING","companyname":"FYEO","companyurl":"https://www.fyeo.io/careers","id":"fyeo8","companycategory":"DID"},{"companyname":"FYEO","jobname":" Product Manager - FYEO Identity","companyurl":"https://www.fyeo.io/careers","id":"fyeo9","companycategory":"DID","joburl":"https://www.fyeo.io/careers-product-manager-fyeo-id","jobcategory":"PRODUCT"},{"companyname":"FYEO","jobname":" Product Manager - FYEO Domain Intelligence","jobcategory":"PRODUCT","companyurl":"https://www.fyeo.io/careers","companycategory":"DID","joburl":"https://www.fyeo.io/careers-product-manager-fyeo-di","id":"fyeo10"},{"joburl":"https://www.fyeo.io/careers-blockchain-business-development-lead","companycategory":"DID","id":"fyeo11","jobname":"Business Development Lead","jobcategory":"SALES","companyurl":"https://www.fyeo.io/careers","companyname":"FYEO"}]